quart_discord_oauth/__init__.py
quart_discord_oauth/discord_oauth.py
quart_discord_oauth/exeptions.py
quart_discord_oauth/models/__init__.py
quart_discord_oauth/models/base.py
quart_discord_oauth/models/guild.py
quart_discord_oauth/models/user.py
quart_discord_oauth-1.0.8.dist-info/METADATA
quart_discord_oauth-1.0.8.dist-info/WHEEL
quart_discord_oauth-1.0.8.dist-info/top_level.txt
quart_discord_oauth-1.0.8.dist-info/RECORD
